Metadata-Version: 2.1
Name: odoo14-addon-account-payment-purchase-stock
Version: 14.0.1.0.1
Summary: Integrate Account Payment Purchase with Stock
Home-page: https://github.com/OCA/bank-payment
Author: Akretion, Tecnativa, Odoo Community Association (OCA)
Author-email: support@odoo-community.org
License: AGPL-3
Platform: UNKNOWN
Classifier: Programming Language :: Python
Classifier: Framework :: Odoo
Classifier: Framework :: Odoo :: 14.0
Classifier: License :: OSI Approved :: GNU Affero General Public License v3
Requires-Python: >=3.6
Requires-Dist: odoo14-addon-account-payment-purchase
Requires-Dist: odoo (<14.1dev,>=14.0a)
